MANIFEST.in
README.md
setup.py
structpack/__init__.py
structpack/_version.py
structpack/structpack.py
structpack.egg-info/PKG-INFO
structpack.egg-info/SOURCES.txt
structpack.egg-info/dependency_links.txt
structpack.egg-info/top_level.txt