Metadata-Version: 1.1
Name: structpack
Version: 1.6.0
Summary: A Python library for serializing and deserializing object trees to JSON-compatable values (dicts, lists, strings, ints, floats, bools).
Home-page: https://github.com/Knio/structpack
Author: Tom Flanagan
Author-email: tom@zkpq.ca
License: MIT
Platform: UNKNOWN
Classifier: Intended Audience :: Developers
Classifier: License :: OSI Approved :: MIT License
Classifier: Operating System :: OS Independent
Classifier: Programming Language :: Python
